{
    "homepage": "https://ece.uwaterloo.ca/~aplevich/dpic/",
    "description": "Dpic is an implementation of the pic little language for creating line drawings and illustrations for documents, web pages, and other uses.",
    "license": "BSD",
    "version": "2020.09.15",
    "hash": "a2b46e3e726dcfd9bc7f5ce7b4e36513cce49b6df29fa0e139f7ab0f41f2e5c9",
    "url": "https://ece.uwaterloo.ca/~aplevich/dpic/Windows/dpic.exe",
    "bin": "dpic.exe",
    "checkver": "downloads for ([\\d.]+):",
    "autoupdate": {
        "url": "https://ece.uwaterloo.ca/~aplevich/dpic/Windows/dpic.exe"
    }
}
